django_cli/__init__.py
django_cli/cli.py
django_cli/config.py
django_cli/const.py
django_cli/utils.py
django_cli/core/BaseCommand.py
django_cli/core/__init__.py
django_cli/setup_project/__init__.py
django_cli/setup_project/handler.py
django_cli/setup_project/model.py
django_cli/setup_project/prompt.py
django_cli/template/__init__.py
django_cli/template/asgi.template
django_cli/template/config.template
django_cli/template/gitignore.template
django_cli/template/manage.template
django_cli/template/readme.template
django_cli/template/routing.template
django_cli/template/settings.template
django_cli/template/template.yaml
django_cli/template/urls.template
django_cli/template/wsgi.template
django_setup_cli-1.0.17.dist-info/LICENSE
django_setup_cli-1.0.17.dist-info/METADATA
django_setup_cli-1.0.17.dist-info/WHEEL
django_setup_cli-1.0.17.dist-info/entry_points.txt
django_setup_cli-1.0.17.dist-info/top_level.txt
django_setup_cli-1.0.17.dist-info/RECORD
