Metadata-Version: 2.1
Name: django-setup-cli
Version: 1.0.17
Summary: django-setup-cli helps to produce production ready django project
Home-page: https://github.com/khan-asfi-reza/django-setup-cli
Author: Khan Asfi Reza
Author-email: khanasfireza10@gmail.com
License: UNKNOWN
Platform: UNKNOWN
Classifier: Programming Language :: Python :: 3
Classifier: License :: OSI Approved :: MIT License
Classifier: Operating System :: OS Independent
Requires-Python: >=3.6
License-File: LICENSE
Requires-Dist: pyyaml (~=6.0)
Requires-Dist: click (~=8.0.3)
Requires-Dist: python-dotenv (~=0.19.2)
Requires-Dist: django
